{
  "CommandPostFavourite01": "CommandPostFavourites",
  "CommandPostFavourite02": "CommandPostFavourites",
  "CommandPostFavourite03": "CommandPostFavourites",
  "CommandPostFavourite04": "CommandPostFavourites",
  "CommandPostFavourite05": "CommandPostFavourites",
  "CommandPostFavourite06": "CommandPostFavourites",
  "CommandPostFavourite07": "CommandPostFavourites",
  "CommandPostFavourite08": "CommandPostFavourites",
  "CommandPostFavourite09": "CommandPostFavourites",
  "CommandPostFavourite10": "CommandPostFavourites",
  "CommandPostFavourite11": "CommandPostFavourites",
  "CommandPostFavourite12": "CommandPostFavourites",
  "CommandPostFavourite13": "CommandPostFavourites",
  "CommandPostFavourite14": "CommandPostFavourites",
  "CommandPostFavourite15": "CommandPostFavourites",
  "CommandPostFavourite16": "CommandPostFavourites",
  "CommandPostFavourite17": "CommandPostFavourites",
  "CommandPostFavourite18": "CommandPostFavourites",
  "CommandPostFavourite19": "CommandPostFavourites",
  "CommandPostFavourite20": "CommandPostFavourites"
}

